LICENSE
MANIFEST.in
README.md
README.rst
requirements.txt
setup.cfg
setup.py
drf_routers/__init__.py
drf_routers/relations.py
drf_routers/routers.py
drf_routers.egg-info/PKG-INFO
drf_routers.egg-info/SOURCES.txt
drf_routers.egg-info/dependency_links.txt
drf_routers.egg-info/requires.txt
drf_routers.egg-info/top_level.txt
tests/__init__.py
tests/conftest.py
tests/description.py
tests/models.py
tests/test_dummy.py
tests/test_dynamic_routers.py
tests/test_routers.py
tests/tests.py
tests/extras/__init__.py
tests/extras/bad_import.py