Metadata-Version: 1.1
Name: drf-routers
Version: 0.1
Summary: Grouped/Nested resources for the Django Rest Framework
Home-page: https://github.com/tranvietanh1991/drf-routers
Author: V.Anh Tran
Author-email: tranvietanh1991@gmail.com
License: MIT
Download-URL: https://github.com/tranvietanh1991/drf-routers/archive/master.zip
Keywords: django,rest,drf,django-rest-framwork,router,nested,grouped
Platform: UNKNOWN
Classifier: Development Status :: 4 - Beta
Classifier: Environment :: Web Environment
Classifier: Framework :: Django
Classifier: Intended Audience :: Developers
Classifier: Intended Audience :: System Administrators
Classifier: License :: OSI Approved :: MIT License
Classifier: Operating System :: OS Independent
Classifier: Programming Language :: Python :: 2
Classifier: Topic :: Software Development :: Libraries :: Python Modules
